{
  "kind": "multiFirstTsBlock",
  "entries": [
    {
      "docsPath": "../../docs/features/child-processes.mdx",
      "examplePath": "src/child-processes.ts"
    },
    {
      "docsPath": "../../docs/features/filesystem.mdx",
      "examplePath": "src/filesystem.ts"
    },
    {
      "docsPath": "../../docs/features/module-loading.mdx",
      "examplePath": "src/module-loading.ts"
    },
    {
      "docsPath": "../../docs/features/networking.mdx",
      "examplePath": "src/networking.ts"
    },
    {
      "docsPath": "../../docs/features/output-capture.mdx",
      "examplePath": "src/output-capture.ts"
    },
    {
      "docsPath": "../../docs/features/permissions.mdx",
      "examplePath": "src/permissions.ts"
    },
    {
      "docsPath": "../../docs/features/resource-limits.mdx",
      "examplePath": "src/resource-limits.ts"
    },
    {
      "docsPath": "../../docs/features/typescript.mdx",
      "examplePath": "src/typescript.ts"
    },
    {
      "docsPath": "../../docs/features/virtual-filesystem.mdx",
      "examplePath": "src/virtual-filesystem.ts"
    }
  ],
  "importReplacements": [
    {
      "from": "\"../../../packages/secure-exec/src/index.ts\"",
      "to": "\"secure-exec\""
    },
    {
      "from": "\"../../../packages/secure-exec/src/types.ts\"",
      "to": "\"secure-exec\""
    },
    {
      "from": "\"../../../packages/typescript/src/index.ts\"",
      "to": "\"@secure-exec/typescript\""
    }
  ]
}
